tmnd/__init__.py
tmnd/configuration.py
tmnd/display.py
tmnd/elements/__init__.py
tmnd/elements/network.py
tmnd/elements/service.py
tmnd/elements/volume.py
tmnd/environments.py
tmnd/tmnd.py
tmnd-0.0.3.dist-info/entry_points.txt
tmnd-0.0.3.dist-info/WHEEL
tmnd-0.0.3.dist-info/METADATA
tmnd-0.0.3.dist-info/RECORD
